dynamanager/__init__.py
dynamanager/exceptions.py
dynamanager/manager.py
dynamanager/utils.py
dynamanager-0.1.5.dist-info/METADATA
dynamanager-0.1.5.dist-info/WHEEL
dynamanager-0.1.5.dist-info/licenses/AUTHORS.md
dynamanager-0.1.5.dist-info/licenses/LICENCE
dynamanager-0.1.5.dist-info/RECORD
