Metadata-Version: 2.4
Name: dynamanager
Version: 0.1.5
Summary: Straightforward application config management powered by Dynaconf
License: MIT
License-File: AUTHORS.md
License-File: LICENCE
Keywords: dynaconf,settings,settings file,settings manager,toml,configuration,configuration manager
Author: The Galactipy Contributors
Author-email: mpq.dev@pm.me
Maintainer: The Galactipy Contributors
Maintainer-email: mpq.dev@pm.me
Requires-Python: >=3.9
Classifier: Development Status :: 1 - Planning
Classifier: Intended Audience :: Developers
Classifier: License :: OSI Approved :: MIT License
Classifier: Operating System :: OS Independent
Classifier: Programming Language :: Python :: 3
Classifier: Programming Language :: Python :: 3.9
Classifier: Programming Language :: Python :: 3.10
Classifier: Programming Language :: Python :: 3.11
Classifier: Programming Language :: Python :: 3.12
Classifier: Programming Language :: Python :: 3.13
Classifier: Programming Language :: Python :: 3.14
Classifier: Topic :: Software Development :: Libraries :: Python Modules
Requires-Dist: deepdiff (>=8.6.0,<9.0.0)
Requires-Dist: dynaconf (>=3.2.11,<4.0.0)
Requires-Dist: loguru (>=0.7.3,<0.8.0)
Requires-Dist: tomlkit (>=0.13.3,<0.14.0)
Project-URL: Contributing Guidelines, https://gitlab.com/galactipy/dynamanager/-/tree/master/CONTRIBUTING.md
Project-URL: Homepage, https://gitlab.com/galactipy/dynamanager
Project-URL: Repository, https://gitlab.com/galactipy/dynamanager
Project-URL: Work Item Tracker, https://gitlab.com/galactipy/dynamanager/-/issues
